carbonaware_scheduler/__init__.py
carbonaware_scheduler/_base_client.py
carbonaware_scheduler/_client.py
carbonaware_scheduler/_compat.py
carbonaware_scheduler/_constants.py
carbonaware_scheduler/_exceptions.py
carbonaware_scheduler/_files.py
carbonaware_scheduler/_models.py
carbonaware_scheduler/_qs.py
carbonaware_scheduler/_resource.py
carbonaware_scheduler/_response.py
carbonaware_scheduler/_streaming.py
carbonaware_scheduler/_types.py
carbonaware_scheduler/_version.py
carbonaware_scheduler/py.typed
carbonaware_scheduler/_utils/__init__.py
carbonaware_scheduler/_utils/_logs.py
carbonaware_scheduler/_utils/_proxy.py
carbonaware_scheduler/_utils/_reflection.py
carbonaware_scheduler/_utils/_resources_proxy.py
carbonaware_scheduler/_utils/_streams.py
carbonaware_scheduler/_utils/_sync.py
carbonaware_scheduler/_utils/_transform.py
carbonaware_scheduler/_utils/_typing.py
carbonaware_scheduler/_utils/_utils.py
carbonaware_scheduler/lib/.keep
carbonaware_scheduler/lib/introspection.py
carbonaware_scheduler/resources/__init__.py
carbonaware_scheduler/resources/health.py
carbonaware_scheduler/resources/regions.py
carbonaware_scheduler/resources/schedule.py
carbonaware_scheduler/types/__init__.py
carbonaware_scheduler/types/cloud_zone.py
carbonaware_scheduler/types/cloud_zone_param.py
carbonaware_scheduler/types/health_check_response.py
carbonaware_scheduler/types/region_list_response.py
carbonaware_scheduler/types/retrieve_response.py
carbonaware_scheduler/types/schedule_create_params.py
carbonaware_scheduler/types/schedule_create_response.py
carbonaware_scheduler/types/schedule_option.py
carbonaware_scheduler_client-1.3.0.dist-info/METADATA
carbonaware_scheduler_client-1.3.0.dist-info/WHEEL
carbonaware_scheduler_client-1.3.0.dist-info/licenses/LICENSE
carbonaware_scheduler_client-1.3.0.dist-info/RECORD
